pysqlcon/__init__.py
pysqlcon/base.py
pysqlcon/errors.py
pysqlcon/orm.py
pysqlcon/queryset.py
pysqlcon-0.5.dist-info/DESCRIPTION.rst
pysqlcon-0.5.dist-info/METADATA
pysqlcon-0.5.dist-info/RECORD
pysqlcon-0.5.dist-info/WHEEL
pysqlcon-0.5.dist-info/metadata.json
pysqlcon-0.5.dist-info/top_level.txt
