Metadata-Version: 2.0
Name: pysqlcon
Version: 0.5
Summary: Easy execution of sql statements and stored procedures on MSSQL database
Home-page: https://github.com/kudzaitsapo/pysqlcon
Author: Kudzai Tsapo
Author-email: kudzai@charteredsys.com
License: MIT
Platform: UNKNOWN
